{
  "name": "Java",
  "image": "mcr.microsoft.com/devcontainers/java:17-bullseye",

  "features": {
    "ghcr.io/devcontainers/features/java:1": {
      "version": "none",
      "installMaven": "true",
      "installGradle": "false"
    }
  },

  
  "postCreateCommand": "apt-get update && apt-get install -y sqlite3",


  "postStartCommand": "command -v sqlite3 >/dev/null || (apt-get update && apt-get install -y sqlite3)",

  "customizations": {
    "vscode": {
      "settings": {
        "sqlite.sqlite3": "/usr/bin/sqlite3"
      },
      "extensions": [
        "alexcvzz.vscode-sqlite"
      ]
    }
  }
}
